{
  "providers": {
    "aave": {
      "name": "Aave v3",
      "maxCapacity": 35000000,
      "successRate": 98.9,
      "feeStructure": 0.0009,
      "supportedAssets": ["ETH", "USDC", "USDT", "DAI", "WBTC"],
      "minLoan": 100000,
      "maxLoan": 5000000
    },
    "dydx": {
      "name": "dYdX",
      "maxCapacity": 25000000,
      "successRate": 97.8,
      "feeStructure": 0.0012,
      "supportedAssets": ["ETH", "USDC", "DAI"],
      "minLoan": 50000,
      "maxLoan": 3000000
    },
    "uniswap": {
      "name": "Uniswap v3",
      "maxCapacity": 5000000,
      "successRate": 96.5,
      "feeStructure": 0.0015,
      "supportedAssets": ["ETH", "USDC", "USDT", "DAI"],
      "minLoan": 10000,
      "maxLoan": 1000000
    },
    "compound": {
      "name": "Compound",
      "maxCapacity": 3000000,
      "successRate": 98.2,
      "feeStructure": 0.0010,
      "supportedAssets": ["ETH", "USDC", "DAI"],
      "minLoan": 5000,
      "maxLoan": 500000
    }
  },
  "routing": {
    "priority": ["aave", "dydx", "compound", "uniswap"],
    "fallbackEnabled": true,
    "autoRetry": true,
    "maxRetries": 3
  }
}
